odpath/__init__.py
odpath/src.py
odpath-0.0.7.dist-info/LICENSE
odpath-0.0.7.dist-info/METADATA
odpath-0.0.7.dist-info/WHEEL
odpath-0.0.7.dist-info/top_level.txt
odpath-0.0.7.dist-info/RECORD
