Metadata-Version: 2.1
Name: odpath
Version: 0.0.7
Summary: get files path and name
Home-page: UNKNOWN
Author: Guodong Wu
Author-email: 461854822@qq.com
License: MIT
Keywords: file path
Platform: UNKNOWN
Classifier: Development Status :: 4 - Beta
Classifier: Intended Audience :: Developers
Classifier: Topic :: Scientific/Engineering :: Artificial Intelligence
Classifier: License :: OSI Approved :: MIT License
Classifier: Programming Language :: Python :: 3.6
Classifier: Programming Language :: Python :: 3.7
Classifier: Programming Language :: Python :: 3.8
Classifier: Programming Language :: Python :: 3.9
Classifier: Programming Language :: Python :: 3.10
Classifier: Programming Language :: Python :: 3.11
Requires-Dist: tqdm
Requires-Dist: cython
Requires-Dist: opencv-python
Requires-Dist: typing-extensions
Requires-Dist: future
Requires-Dist: tensorboard
Requires-Dist: scikit-image
Requires-Dist: pillow
Requires-Dist: numpy (<2.0)
Requires-Dist: loguru
Requires-Dist: gevent
Requires-Dist: matplotlib
Requires-Dist: fastapi
Requires-Dist: uvicorn
Requires-Dist: Flask (==2.2.0)
Requires-Dist: requests (==2.28.1)
Requires-Dist: flask-cors (==3.0.10)
Requires-Dist: Werkzeug (==2.2.2)
Requires-Dist: concurrent-log-handler
